nmross/NMRoss.py
nmross/__init__.py
nmross-0.0.1.dist-info/LICENSE
nmross-0.0.1.dist-info/METADATA
nmross-0.0.1.dist-info/WHEEL
nmross-0.0.1.dist-info/top_level.txt
nmross-0.0.1.dist-info/RECORD
