Metadata-Version: 2.1
Name: nmross
Version: 0.0.1
Summary: Gives an approximate 1H NMR when given a smiles or a IUPAC name of a molecule with maximum one aromatic ring and no double bonds.
Author-email: Cedric Rossboth <cedric.rossboth@epfl.ch>
License: MIT License
Project-URL: source, https://github.com/CedricRossboth/nmross
Project-URL: tracker, https://github.com/CedricRossboth/nmross/issues
Keywords: NMR
Classifier: Development Status :: 3 - Alpha
Classifier: Intended Audience :: Developers
Classifier: License :: OSI Approved :: MIT License
Classifier: Operating System :: OS Independent
Classifier: Programming Language :: Python
Classifier: Programming Language :: Python :: 3
Classifier: Programming Language :: Python :: 3.8
Classifier: Programming Language :: Python :: 3.9
Classifier: Programming Language :: Python :: 3.10
Classifier: Programming Language :: Python :: 3.11
Requires-Python: >=3.10
License-File: LICENSE
Requires-Dist: pubchempy ==1.0.4
Requires-Dist: numpy
Requires-Dist: rdkit
Requires-Dist: matplotlib
Provides-Extra: doc
Requires-Dist: furo ; extra == 'doc'
Requires-Dist: myst-parser ; extra == 'doc'
Requires-Dist: sphinx >=5 ; extra == 'doc'
Requires-Dist: sphinx-copybutton ; extra == 'doc'
Provides-Extra: test
Requires-Dist: hypothesis ; extra == 'test'
Requires-Dist: pytest ; extra == 'test'
Requires-Dist: pytest-cov ; extra == 'test'
Requires-Dist: tox ; extra == 'test'
Requires-Dist: genbadge[coverage] ; extra == 'test'
